pproto_py/__init__.py
pproto_py/app.py
pproto_py/base/__init__.py
pproto_py/base/base.py
pproto_py/client/__init__.py
pproto_py/client/client.py
pproto_py/content/__init__.py
pproto_py/content/content.py
pproto_py/content/decorators.py
pproto_py/core/__init__.py
pproto_py/core/commands.py
pproto_py/core/exceptions.py
pproto_py/core/logger.py
pproto_py/schemas/__init__.py
pproto_py/schemas/exceptions.py
pproto_py/schemas/message.py
pproto_py/server/__init__.py
pproto_py/server/router.py
pproto_py/server/server.py
pproto_py-2.1.3.dist-info/METADATA
pproto_py-2.1.3.dist-info/WHEEL
pproto_py-2.1.3.dist-info/top_level.txt
pproto_py-2.1.3.dist-info/RECORD
